{"NIFTY": {"symbol": "NIFTY", "spot": 23998.75, "atm": 24000, "step": 50, "expiry": "2026-05-05", "strikeCount": 11, "strikes": [{"strike": 23750, "label": "ITM-5", "isATM": false, "ce": {"signal": "STRONG_SELL", "score": -55.4, "breakdown": {"buyPct": 29, "sellPct": 66, "neutralPct": 5}, "oi": 239850, "oiChange": 0, "volume": 8863985, "price": 369.8, "change": -126.8, "signals": {"liq": "SSL", "bos": "DOWN", "delta": 0.694, "trap": false, "oiInterp": null, "iv": 0.1905, "gamma": 0.00066, "theta": -21.66, "vega": 9.85}, "velocity": "COLD"}, "pe": {"signal": "STRONG_BUY", "score": 73.7, "breakdown": {"buyPct": 73, "sellPct": 24, "neutralPct": 3}, "oi": 1238380, "oiChange": 0, "volume": 37772345, "price": 77.3, "change": 24.75, "signals": {"liq": "SSL", "bos": "DOWN", "delta": -0.275, "trap": false, "oiInterp": null, "iv": 0.1609, "gamma": 0.00074, "theta": -13.89, "vega": 9.37}, "velocity": "COLD"}}, {"strike": 23800, "label": "ITM-4", "isATM": false, "ce": {"signal": "STRONG_SELL", "score": -46.7, "breakdown": {"buyPct": 32, "sellPct": 63, "neutralPct": 5}, "oi": 1241435, "oiChange": 0, "volume": 63972480, "price": 331.9, "change": -124.4, "signals": {"liq": "SSL", "bos": "DOWN", "delta": 0.664, "trap": false, "oiInterp": null, "iv": 0.1861, "gamma": 0.0007, "theta": -21.85, "vega": 10.25}, "velocity": "COLD"}, "pe": {"signal": "STRONG_BUY", "score": 61.6, "breakdown": {"buyPct": 68, "sellPct": 28, "neutralPct": 4}, "oi": 4334720, "oiChange": 0, "volume": 122502900, "price": 89.4, "change": 27.85, "signals": {"liq": "SSL", "bos": "DOWN", "delta": -0.311, "trap": false, "oiInterp": null, "iv": 0.1579, "gamma": 0.0008, "theta": -14.31, "vega": 9.92}, "velocity": "WARM"}}, {"strike": 23850, "label": "ITM-3", "isATM": false, "ce": {"signal": "STRONG_SELL", "score": -47.8, "breakdown": {"buyPct": 32, "sellPct": 63, "neutralPct": 5}, "oi": 767715, "oiChange": 0, "volume": 45748105, "price": 297.15, "change": -116.45, "signals": {"liq": "SSL", "bos": "DOWN", "delta": 0.629, "trap": false, "oiInterp": null, "iv": 0.1834, "gamma": 0.00073, "theta": -22.09, "vega": 10.61}, "velocity": "COLD"}, "pe": {"signal": "STRONG_BUY", "score": 59.0, "breakdown": {"buyPct": 68, "sellPct": 28, "neutralPct": 4}, "oi": 1865110, "oiChange": 0, "volume": 74216415, "price": 104.5, "change": 34.35, "signals": {"liq": "SSL", "bos": "DOWN", "delta": -0.35, "trap": false, "oiInterp": null, "iv": 0.1562, "gamma": 0.00084, "theta": -14.74, "vega": 10.4}, "velocity": "COLD"}}, {"strike": 23900, "label": "ITM-2", "isATM": false, "ce": {"signal": "SELL", "score": -44.8, "breakdown": {"buyPct": 33, "sellPct": 62, "neutralPct": 5}, "oi": 1728545, "oiChange": 0, "volume": 105020630, "price": 263.85, "change": -114.4, "signals": {"liq": "SSL", "bos": "DOWN", "delta": 0.593, "trap": false, "oiInterp": null, "iv": 0.1805, "gamma": 0.00077, "theta": -22.15, "vega": 10.89}, "velocity": "COLD"}, "pe": {"signal": "STRONG_BUY", "score": 54.0, "breakdown": {"buyPct": 65, "sellPct": 30, "neutralPct": 5}, "oi": 3567395, "oiChange": 0, "volume": 129102740, "price": 120.9, "change": 37.6, "signals": {"liq": "SSL", "bos": "DOWN", "delta": -0.392, "trap": false, "oiInterp": null, "iv": 0.1539, "gamma": 0.00089, "theta": -14.91, "vega": 10.79}, "velocity": "COLD"}}, {"strike": 23950, "label": "ITM-1", "isATM": false, "ce": {"signal": "SELL", "score": -23.4, "breakdown": {"buyPct": 39, "sellPct": 54, "neutralPct": 7}, "oi": 1070940, "oiChange": 0, "volume": 60619650, "price": 232.6, "change": -107.7, "signals": {"liq": "SSL", "bos": "DOWN", "delta": 0.555, "trap": false, "oiInterp": null, "iv": 0.1778, "gamma": 0.00079, "theta": -22.06, "vega": 11.1}, "velocity": "COLD"}, "pe": {"signal": "BUY", "score": 30.5, "breakdown": {"buyPct": 56, "sellPct": 37, "neutralPct": 7}, "oi": 1842750, "oiChange": 0, "volume": 60470800, "price": 139.0, "change": 42.8, "signals": {"liq": "SSL", "bos": "DOWN", "delta": -0.436, "trap": false, "oiInterp": null, "iv": 0.1512, "gamma": 0.00093, "theta": -14.83, "vega": 11.06}, "velocity": "COLD"}}, {"strike": 24000, "label": "ATM", "isATM": true, "ce": {"signal": "SELL", "score": -26.5, "breakdown": {"buyPct": 38, "sellPct": 55, "neutralPct": 7}, "oi": 5716490, "oiChange": 0, "volume": 152604855, "price": 203.25, "change": -103.1, "signals": {"liq": null, "bos": "DOWN", "delta": 0.516, "trap": false, "oiInterp": null, "iv": 0.1751, "gamma": 0.00081, "theta": -21.77, "vega": 11.19}, "velocity": "COLD"}, "pe": {"signal": "BUY", "score": 26.6, "breakdown": {"buyPct": 55, "sellPct": 38, "neutralPct": 7}, "oi": 5754710, "oiChange": 0, "volume": 126338030, "price": 159.9, "change": 48.8, "signals": {"liq": null, "bos": "DOWN", "delta": -0.483, "trap": false, "oiInterp": null, "iv": 0.149, "gamma": 0.00095, "theta": -14.59, "vega": 11.19}, "velocity": "COLD"}}, {"strike": 24050, "label": "OTM+1", "isATM": false, "ce": {"signal": "SELL", "score": -37.8, "breakdown": {"buyPct": 35, "sellPct": 59, "neutralPct": 6}, "oi": 1597245, "oiChange": 0, "volume": 52323570, "price": 176.7, "change": -96.3, "signals": {"liq": "BSL", "bos": "DOWN", "delta": 0.475, "trap": true, "oiInterp": null, "iv": 0.1731, "gamma": 0.00082, "theta": -21.35, "vega": 11.18}, "velocity": "COLD"}, "pe": {"signal": "BUY", "score": 20.4, "breakdown": {"buyPct": 53, "sellPct": 40, "neutralPct": 7}, "oi": 1370395, "oiChange": 0, "volume": 30795765, "price": 182.6, "change": 54.65, "signals": {"liq": "BSL", "bos": "DOWN", "delta": -0.531, "trap": false, "oiInterp": null, "iv": 0.1464, "gamma": 0.00097, "theta": -14.05, "vega": 11.17}, "velocity": "COLD"}}, {"strike": 24100, "label": "OTM+2", "isATM": false, "ce": {"signal": "SELL", "score": -39.3, "breakdown": {"buyPct": 34, "sellPct": 60, "neutralPct": 6}, "oi": 3231085, "oiChange": 0, "volume": 74804210, "price": 152.25, "change": -91.25, "signals": {"liq": "BSL", "bos": "DOWN", "delta": 0.433, "trap": true, "oiInterp": null, "iv": 0.1711, "gamma": 0.00082, "theta": -20.72, "vega": 11.05}, "velocity": "COLD"}, "pe": {"signal": "NEUTRAL", "score": 15.5, "breakdown": {"buyPct": 51, "sellPct": 41, "neutralPct": 8}, "oi": 1878435, "oiChange": 0, "volume": 34523645, "price": 208.1, "change": 61.3, "signals": {"liq": "BSL", "bos": "DOWN", "delta": -0.58, "trap": false, "oiInterp": null, "iv": 0.144, "gamma": 0.00097, "theta": -13.29, "vega": 10.97}, "velocity": "COLD"}}, {"strike": 24150, "label": "OTM+3", "isATM": false, "ce": {"signal": "SELL", "score": -32.2, "breakdown": {"buyPct": 37, "sellPct": 57, "neutralPct": 6}, "oi": 1151670, "oiChange": 0, "volume": 36562500, "price": 130.45, "change": -83.25, "signals": {"liq": "BSL", "bos": "DOWN", "delta": 0.392, "trap": true, "oiInterp": null, "iv": 0.1697, "gamma": 0.00081, "theta": -19.96, "vega": 10.79}, "velocity": "COLD"}, "pe": {"signal": "NEUTRAL", "score": 4.9, "breakdown": {"buyPct": 47, "sellPct": 44, "neutralPct": 9}, "oi": 520780, "oiChange": 0, "volume": 8035690, "price": 237.05, "change": 69.7, "signals": {"liq": "BSL", "bos": "DOWN", "delta": -0.629, "trap": false, "oiInterp": null, "iv": 0.1426, "gamma": 0.00094, "theta": -12.4, "vega": 10.61}, "velocity": "COLD"}}, {"strike": 24200, "label": "OTM+4", "isATM": false, "ce": {"signal": "SELL", "score": -33.6, "breakdown": {"buyPct": 36, "sellPct": 58, "neutralPct": 6}, "oi": 4413370, "oiChange": 0, "volume": 78792545, "price": 110.85, "change": -76.95, "signals": {"liq": "BSL", "bos": "DOWN", "delta": 0.352, "trap": true, "oiInterp": null, "iv": 0.1684, "gamma": 0.00078, "theta": -19.03, "vega": 10.42}, "velocity": "COLD"}, "pe": {"signal": "NEUTRAL", "score": 6.0, "breakdown": {"buyPct": 47, "sellPct": 44, "neutralPct": 9}, "oi": 1951300, "oiChange": 0, "volume": 17668300, "price": 267.9, "change": 78.3, "signals": {"liq": "BSL", "bos": "DOWN", "delta": -0.677, "trap": false, "oiInterp": null, "iv": 0.1406, "gamma": 0.00091, "theta": -11.23, "vega": 10.08}, "velocity": "COLD"}}, {"strike": 24250, "label": "OTM+5", "isATM": false, "ce": {"signal": "SELL", "score": -32.4, "breakdown": {"buyPct": 37, "sellPct": 57, "neutralPct": 6}, "oi": 1411085, "oiChange": 0, "volume": 30982770, "price": 94.05, "change": -69.75, "signals": {"liq": "BSL", "bos": "DOWN", "delta": 0.313, "trap": true, "oiInterp": null, "iv": 0.1678, "gamma": 0.00075, "theta": -18.01, "vega": 9.95}, "velocity": "COLD"}, "pe": {"signal": "NEUTRAL", "score": -2.8, "breakdown": {"buyPct": 45, "sellPct": 46, "neutralPct": 9}, "oi": 336310, "oiChange": 0, "volume": 2935530, "price": 300.6, "change": 87.1, "signals": {"liq": "BSL", "bos": "DOWN", "delta": -0.725, "trap": false, "oiInterp": null, "iv": 0.1379, "gamma": 0.00086, "theta": -9.77, "vega": 9.37}, "velocity": "COLD"}}], "intelligence": {"symbol": "NIFTY", "signal": "STRONG_SELL", "score": -93.2, "confidence": 96, "regime": "TRENDING", "agreementPct": 100, "bullPressure": 0, "bearPressure": 100, "trapRiskPct": 45, "actionability": "MEDIUM", "confidenceReason": "Live chain with current confidence model", "pcr": 1.09, "maxPain": 24000, "maxPainGapPct": 0.03, "keyLevels": {"support": 24000, "resistance": 24000, "supportGapPct": -0.03, "resistanceGapPct": 0.03}, "bestStrike": {"strike": 23850, "label": "ITM-3", "side": "CE", "direction": "UP", "score": 79.4, "confidence": 100, "reason": "STRONG SELL CE at ITM-3 (75% conviction)", "greeksSummary": "\u03940.63 | \u0398-22 | \u03c318%"}, "pricePredictions": {"lowestItmCe": {"price": 232.6, "strike": 23950, "direction": "DOWN", "confidence": 55, "signal": "SELL", "velocity": "COLD"}, "lowestOtmCe": {"price": 94.05, "strike": 24250, "direction": "DOWN", "confidence": 55, "signal": "SELL", "velocity": "COLD"}, "lowestItmPe": {"price": 159.9, "strike": 24000, "direction": "UP", "confidence": 55, "signal": "BUY", "velocity": "COLD"}, "lowestOtmPe": {"price": 77.3, "strike": 23750, "direction": "UP", "confidence": 70, "signal": "STRONG_BUY", "velocity": "COLD"}}, "insights": ["Flow bias: STRONG SELL (-93.2)", "Agreement 100% across active strikes", "Key levels S:24000 | R:24000", "BOS confirms downside continuation"]}, "dataSource": "LAST_CLOSE", "timestamp": "2026-04-30T15:22:19.929950+05:30", "spotUpdatedAt": "2026-04-30T15:22:19.929950+05:30", "optionChainUpdatedAt": "2026-04-30T15:22:13.961440+05:30", "optionChainAgeSec": 256626.6, "feedMode": "HYBRID_LIVE"}, "BANKNIFTY": {"symbol": "BANKNIFTY", "spot": 54860.75, "atm": 54900, "step": 100, "expiry": "2026-05-26", "strikeCount": 11, "strikes": [{"strike": 54400, "label": "ITM-5", "isATM": false, "ce": {"signal": "STRONG_SELL", "score": -56.9, "breakdown": {"buyPct": 30, "sellPct": 66, "neutralPct": 4}, "oi": 15720, "oiChange": 0, "volume": 146970, "price": 1637.65, "change": -335.8, "signals": {"liq": "SSL", "bos": "DOWN", "delta": 0.6, "trap": false, "oiInterp": null, "iv": 0.2162, "gamma": 0.00012, "theta": -29.09, "vega": 56.57}, "velocity": "COLD"}, "pe": {"signal": "STRONG_BUY", "score": 66.0, "breakdown": {"buyPct": 70, "sellPct": 26, "neutralPct": 4}, "oi": 30300, "oiChange": 0, "volume": 372840, "price": 840.65, "change": 161.75, "signals": {"liq": "SSL", "bos": "DOWN", "delta": -0.394, "trap": false, "oiInterp": null, "iv": 0.1997, "gamma": 0.00013, "theta": -17.63, "vega": 56.33}, "velocity": "COLD"}}, {"strike": 54500, "label": "ITM-4", "isATM": false, "ce": {"signal": "STRONG_SELL", "score": -51.0, "breakdown": {"buyPct": 31, "sellPct": 64, "neutralPct": 5}, "oi": 94170, "oiChange": 0, "volume": 936420, "price": 1566.6, "change": -268.65, "signals": {"liq": "SSL", "bos": "DOWN", "delta": 0.588, "trap": false, "oiInterp": null, "iv": 0.2137, "gamma": 0.00012, "theta": -28.88, "vega": 56.97}, "velocity": "COLD"}, "pe": {"signal": "STRONG_BUY", "score": 62.0, "breakdown": {"buyPct": 68, "sellPct": 28, "neutralPct": 4}, "oi": 218430, "oiChange": 0, "volume": 1751340, "price": 876.7, "change": 166.2, "signals": {"liq": "SSL", "bos": "DOWN", "delta": -0.407, "trap": false, "oiInterp": null, "iv": 0.1986, "gamma": 0.00013, "theta": -17.57, "vega": 56.81}, "velocity": "COLD"}}, {"strike": 54600, "label": "ITM-3", "isATM": false, "ce": {"signal": "STRONG_SELL", "score": -51.1, "breakdown": {"buyPct": 31, "sellPct": 64, "neutralPct": 5}, "oi": 32340, "oiChange": 0, "volume": 601080, "price": 1506.45, "change": -244.05, "signals": {"liq": "SSL", "bos": "DOWN", "delta": 0.576, "trap": false, "oiInterp": null, "iv": 0.213, "gamma": 0.00013, "theta": -28.85, "vega": 57.35}, "velocity": "COLD"}, "pe": {"signal": "STRONG_BUY", "score": 57.3, "breakdown": {"buyPct": 67, "sellPct": 29, "neutralPct": 4}, "oi": 50640, "oiChange": 0, "volume": 879780, "price": 912.95, "change": 172.2, "signals": {"liq": "SSL", "bos": "DOWN", "delta": -0.42, "trap": false, "oiInterp": null, "iv": 0.1974, "gamma": 0.00014, "theta": -17.46, "vega": 57.23}, "velocity": "COLD"}}, {"strike": 54700, "label": "ITM-2", "isATM": false, "ce": {"signal": "STRONG_SELL", "score": -47.7, "breakdown": {"buyPct": 32, "sellPct": 63, "neutralPct": 5}, "oi": 32430, "oiChange": 0, "volume": 717870, "price": 1441.65, "change": -234.6, "signals": {"liq": "SSL", "bos": "DOWN", "delta": 0.563, "trap": false, "oiInterp": null, "iv": 0.2112, "gamma": 0.00013, "theta": -28.67, "vega": 57.66}, "velocity": "COLD"}, "pe": {"signal": "STRONG_BUY", "score": 54.8, "breakdown": {"buyPct": 65, "sellPct": 30, "neutralPct": 5}, "oi": 54870, "oiChange": 0, "volume": 882030, "price": 948.05, "change": 179.0, "signals": {"liq": "SSL", "bos": "DOWN", "delta": -0.433, "trap": false, "oiInterp": null, "iv": 0.1958, "gamma": 0.00014, "theta": -17.28, "vega": 57.59}, "velocity": "COLD"}}, {"strike": 54800, "label": "ITM-1", "isATM": false, "ce": {"signal": "STRONG_SELL", "score": -51.3, "breakdown": {"buyPct": 31, "sellPct": 64, "neutralPct": 5}, "oi": 39330, "oiChange": 0, "volume": 639240, "price": 1388.95, "change": -251.75, "signals": {"liq": "SSL", "bos": "DOWN", "delta": 0.551, "trap": false, "oiInterp": null, "iv": 0.2113, "gamma": 0.00013, "theta": -28.67, "vega": 57.93}, "velocity": "COLD"}, "pe": {"signal": "STRONG_BUY", "score": 56.8, "breakdown": {"buyPct": 67, "sellPct": 29, "neutralPct": 4}, "oi": 59310, "oiChange": 0, "volume": 868140, "price": 992.0, "change": 183.3, "signals": {"liq": "SSL", "bos": "DOWN", "delta": -0.447, "trap": false, "oiInterp": null, "iv": 0.1954, "gamma": 0.00014, "theta": -17.21, "vega": 57.89}, "velocity": "COLD"}}, {"strike": 54900, "label": "ATM", "isATM": true, "ce": {"signal": "STRONG_SELL", "score": -54.1, "breakdown": {"buyPct": 30, "sellPct": 65, "neutralPct": 5}, "oi": 39990, "oiChange": 0, "volume": 411480, "price": 1326.65, "change": -222.95, "signals": {"liq": null, "bos": "DOWN", "delta": 0.538, "trap": false, "oiInterp": null, "iv": 0.2095, "gamma": 0.00013, "theta": -28.44, "vega": 58.14}, "velocity": "COLD"}, "pe": {"signal": "STRONG_BUY", "score": 57.9, "breakdown": {"buyPct": 67, "sellPct": 29, "neutralPct": 4}, "oi": 51240, "oiChange": 0, "volume": 558720, "price": 1031.8, "change": 178.85, "signals": {"liq": null, "bos": "DOWN", "delta": -0.461, "trap": false, "oiInterp": null, "iv": 0.1942, "gamma": 0.00014, "theta": -17.02, "vega": 58.12}, "velocity": "COLD"}}, {"strike": 55000, "label": "OTM+1", "isATM": false, "ce": {"signal": "STRONG_SELL", "score": -49.4, "breakdown": {"buyPct": 31, "sellPct": 64, "neutralPct": 5}, "oi": 461910, "oiChange": 0, "volume": 2700570, "price": 1268.25, "change": -250.6, "signals": {"liq": null, "bos": "DOWN", "delta": 0.525, "trap": false, "oiInterp": null, "iv": 0.2082, "gamma": 0.00013, "theta": -28.24, "vega": 58.29}, "velocity": "COLD"}, "pe": {"signal": "STRONG_BUY", "score": 52.4, "breakdown": {"buyPct": 65, "sellPct": 30, "neutralPct": 5}, "oi": 557970, "oiChange": 0, "volume": 2715450, "price": 1074.8, "change": 206.75, "signals": {"liq": null, "bos": "DOWN", "delta": -0.475, "trap": false, "oiInterp": null, "iv": 0.1932, "gamma": 0.00014, "theta": -16.83, "vega": 58.29}, "velocity": "COLD"}}, {"strike": 55100, "label": "OTM+2", "isATM": false, "ce": {"signal": "SELL", "score": -32.4, "breakdown": {"buyPct": 37, "sellPct": 57, "neutralPct": 6}, "oi": 28200, "oiChange": 0, "volume": 265650, "price": 1213.2, "change": -205.65, "signals": {"liq": "BSL", "bos": "DOWN", "delta": 0.512, "trap": false, "oiInterp": null, "iv": 0.2072, "gamma": 0.00013, "theta": -28.05, "vega": 58.38}, "velocity": "COLD"}, "pe": {"signal": "BUY", "score": 29.5, "breakdown": {"buyPct": 56, "sellPct": 37, "neutralPct": 7}, "oi": 23280, "oiChange": 0, "volume": 245280, "price": 1114.15, "change": 185.2, "signals": {"liq": "BSL", "bos": "DOWN", "delta": -0.489, "trap": false, "oiInterp": null, "iv": 0.1914, "gamma": 0.00014, "theta": -16.52, "vega": 58.38}, "velocity": "COLD"}}, {"strike": 55200, "label": "OTM+3", "isATM": false, "ce": {"signal": "SELL", "score": -45.3, "breakdown": {"buyPct": 33, "sellPct": 62, "neutralPct": 5}, "oi": 75330, "oiChange": 0, "volume": 375420, "price": 1159.15, "change": -224.4, "signals": {"liq": "BSL", "bos": "DOWN", "delta": 0.499, "trap": true, "oiInterp": null, "iv": 0.2062, "gamma": 0.00013, "theta": -27.82, "vega": 58.4}, "velocity": "COLD"}, "pe": {"signal": "BUY", "score": 21.6, "breakdown": {"buyPct": 54, "sellPct": 39, "neutralPct": 7}, "oi": 43020, "oiChange": 0, "volume": 240660, "price": 1164.0, "change": 209.3, "signals": {"liq": "BSL", "bos": "DOWN", "delta": -0.503, "trap": false, "oiInterp": null, "iv": 0.1911, "gamma": 0.00014, "theta": -16.34, "vega": 58.4}, "velocity": "COLD"}}, {"strike": 55300, "label": "OTM+4", "isATM": false, "ce": {"signal": "SELL", "score": -25.5, "breakdown": {"buyPct": 38, "sellPct": 55, "neutralPct": 7}, "oi": 37380, "oiChange": 0, "volume": 238410, "price": 1108.7, "change": -204.05, "signals": {"liq": null, "bos": "DOWN", "delta": 0.485, "trap": false, "oiInterp": null, "iv": 0.2055, "gamma": 0.00013, "theta": -27.61, "vega": 58.37}, "velocity": "COLD"}, "pe": {"signal": "BUY", "score": 26.5, "breakdown": {"buyPct": 55, "sellPct": 38, "neutralPct": 7}, "oi": 38730, "oiChange": 0, "volume": 162990, "price": 1205.95, "change": 197.55, "signals": {"liq": null, "bos": "DOWN", "delta": -0.518, "trap": false, "oiInterp": null, "iv": 0.1892, "gamma": 0.00014, "theta": -15.96, "vega": 58.35}, "velocity": "COLD"}}, {"strike": 55400, "label": "OTM+5", "isATM": false, "ce": {"signal": "SELL", "score": -45.8, "breakdown": {"buyPct": 33, "sellPct": 62, "neutralPct": 5}, "oi": 52620, "oiChange": 0, "volume": 214260, "price": 1056.95, "change": -224.8, "signals": {"liq": "BSL", "bos": "DOWN", "delta": 0.472, "trap": true, "oiInterp": null, "iv": 0.2045, "gamma": 0.00013, "theta": -27.34, "vega": 58.26}, "velocity": "COLD"}, "pe": {"signal": "BUY", "score": 23.2, "breakdown": {"buyPct": 54, "sellPct": 39, "neutralPct": 7}, "oi": 31830, "oiChange": 0, "volume": 136080, "price": 1258.7, "change": 225.9, "signals": {"liq": "BSL", "bos": "DOWN", "delta": -0.532, "trap": false, "oiInterp": null, "iv": 0.189, "gamma": 0.00014, "theta": -15.74, "vega": 58.22}, "velocity": "COLD"}}], "intelligence": {"symbol": "BANKNIFTY", "signal": "STRONG_SELL", "score": -100.0, "confidence": 99, "regime": "TRENDING", "agreementPct": 100, "bullPressure": 0, "bearPressure": 100, "trapRiskPct": 18, "actionability": "HIGH", "confidenceReason": "Live chain with current confidence model", "pcr": 1.28, "maxPain": 55000, "maxPainGapPct": 0.27, "keyLevels": {"support": 54500, "resistance": 55000, "supportGapPct": 0.64, "resistanceGapPct": 0.27}, "bestStrike": {"strike": 54900, "label": "ATM", "side": "PE", "direction": "DOWN", "score": 79.6, "confidence": 100, "reason": "STRONG BUY PE at ATM (75% conviction)", "greeksSummary": "\u0394-0.46 | \u0398-17 | \u03c319%"}, "pricePredictions": {"lowestItmCe": {"price": 1388.95, "strike": 54800, "direction": "DOWN", "confidence": 70, "signal": "STRONG_SELL", "velocity": "COLD"}, "lowestOtmCe": {"price": 1056.95, "strike": 55400, "direction": "DOWN", "confidence": 55, "signal": "SELL", "velocity": "COLD"}, "lowestItmPe": {"price": 1031.8, "strike": 54900, "direction": "UP", "confidence": 70, "signal": "STRONG_BUY", "velocity": "COLD"}, "lowestOtmPe": {"price": 840.65, "strike": 54400, "direction": "UP", "confidence": 70, "signal": "STRONG_BUY", "velocity": "COLD"}}, "insights": ["Flow bias: STRONG SELL (-100.0)", "Agreement 100% across active strikes", "Key levels S:54500 | R:55000", "BOS confirms downside continuation"]}, "dataSource": "LAST_CLOSE", "timestamp": "2026-04-30T15:22:19.929950+05:30", "spotUpdatedAt": "2026-04-30T15:22:19.929950+05:30", "optionChainUpdatedAt": "2026-04-30T15:22:13.982267+05:30", "optionChainAgeSec": 256626.6, "feedMode": "HYBRID_LIVE"}, "SENSEX": {"symbol": "SENSEX", "spot": 76944.5, "atm": 76900, "step": 100, "expiry": "2026-04-30", "strikeCount": 11, "strikes": [{"strike": 76500, "label": "ITM-4", "isATM": false, "ce": {"signal": "SELL", "score": -22.4, "breakdown": {"buyPct": 39, "sellPct": 54, "neutralPct": 7}, "oi": 391680, "oiChange": 0, "volume": 220031540, "price": 402.4, "change": -661.45, "signals": {"liq": "SSL", "bos": "UP", "delta": 0.546, "trap": false, "oiInterp": null, "iv": null, "gamma": null, "theta": null, "vega": null}, "velocity": "COLD"}, "pe": {"signal": "NEUTRAL", "score": -16.6, "breakdown": {"buyPct": 40, "sellPct": 52, "neutralPct": 8}, "oi": 3285980, "oiChange": 0, "volume": 423406720, "price": 0.1, "change": -48.8, "signals": {"liq": "SSL", "bos": "UP", "delta": 0.454, "trap": false, "oiInterp": null, "iv": null, "gamma": null, "theta": null, "vega": null}, "velocity": "COLD"}}, {"strike": 76600, "label": "ITM-3", "isATM": false, "ce": {"signal": "SELL", "score": -19.9, "breakdown": {"buyPct": 40, "sellPct": 53, "neutralPct": 7}, "oi": 401100, "oiChange": 0, "volume": 202889300, "price": 304.65, "change": -681.95, "signals": {"liq": "SSL", "bos": "UP", "delta": 0.535, "trap": false, "oiInterp": null, "iv": null, "gamma": null, "theta": null, "vega": null}, "velocity": "WARM"}, "pe": {"signal": "SELL", "score": -20.3, "breakdown": {"buyPct": 40, "sellPct": 53, "neutralPct": 7}, "oi": 2728260, "oiChange": 0, "volume": 312074760, "price": 0.1, "change": -58.6, "signals": {"liq": "SSL", "bos": "UP", "delta": 0.465, "trap": false, "oiInterp": null, "iv": null, "gamma": null, "theta": null, "vega": null}, "velocity": "COLD"}}, {"strike": 76700, "label": "ITM-2", "isATM": false, "ce": {"signal": "NEUTRAL", "score": -17.2, "breakdown": {"buyPct": 40, "sellPct": 52, "neutralPct": 8}, "oi": 425560, "oiChange": 0, "volume": 260063640, "price": 203.75, "change": -681.95, "signals": {"liq": "SSL", "bos": "UP", "delta": 0.525, "trap": false, "oiInterp": null, "iv": null, "gamma": null, "theta": null, "vega": null}, "velocity": "COLD"}, "pe": {"signal": "SELL", "score": -21.6, "breakdown": {"buyPct": 40, "sellPct": 53, "neutralPct": 7}, "oi": 3874540, "oiChange": 0, "volume": 356561760, "price": 0.1, "change": -70.0, "signals": {"liq": "SSL", "bos": "UP", "delta": 0.475, "trap": false, "oiInterp": null, "iv": null, "gamma": null, "theta": null, "vega": null}, "velocity": "COLD"}}, {"strike": 76800, "label": "ITM-1", "isATM": false, "ce": {"signal": "SELL", "score": -42.9, "breakdown": {"buyPct": 33, "sellPct": 61, "neutralPct": 6}, "oi": 1459020, "oiChange": 0, "volume": 358554420, "price": 103.6, "change": -700.45, "signals": {"liq": "SSL", "bos": "DOWN", "delta": 0.515, "trap": false, "oiInterp": null, "iv": null, "gamma": null, "theta": null, "vega": null}, "velocity": "COLD"}, "pe": {"signal": "NEUTRAL", "score": 0.3, "breakdown": {"buyPct": 46, "sellPct": 45, "neutralPct": 9}, "oi": 7274920, "oiChange": 0, "volume": 573780860, "price": 0.2, "change": -84.5, "signals": {"liq": "SSL", "bos": "DOWN", "delta": 0.485, "trap": false, "oiInterp": null, "iv": null, "gamma": null, "theta": null, "vega": null}, "velocity": "COLD"}}, {"strike": 76900, "label": "ATM", "isATM": true, "ce": {"signal": "STRONG_SELL", "score": -50.8, "breakdown": {"buyPct": 31, "sellPct": 64, "neutralPct": 5}, "oi": 8169340, "oiChange": 0, "volume": 546526340, "price": 8.7, "change": -721.75, "signals": {"liq": "SSL", "bos": "DOWN", "delta": 0.504, "trap": false, "oiInterp": null, "iv": null, "gamma": null, "theta": null, "vega": null}, "velocity": "EXTREME"}, "pe": {"signal": "NEUTRAL", "score": -6.9, "breakdown": {"buyPct": 43, "sellPct": 48, "neutralPct": 9}, "oi": 9768120, "oiChange": 0, "volume": 640920700, "price": 4.8, "change": -97.6, "signals": {"liq": "SSL", "bos": "DOWN", "delta": -0.164, "trap": false, "oiInterp": null, "iv": 0.0136, "gamma": 0.00451, "theta": -4.52, "vega": 9.95}, "velocity": "EXTREME"}}, {"strike": 77000, "label": "OTM+1", "isATM": false, "ce": {"signal": "SELL", "score": -33.9, "breakdown": {"buyPct": 36, "sellPct": 58, "neutralPct": 6}, "oi": 8803560, "oiChange": 0, "volume": 835485560, "price": 0.35, "change": -651.15, "signals": {"liq": "BSL", "bos": "DOWN", "delta": 0.494, "trap": false, "oiInterp": null, "iv": null, "gamma": null, "theta": null, "vega": null}, "velocity": "COLD"}, "pe": {"signal": "SELL", "score": -41.6, "breakdown": {"buyPct": 33, "sellPct": 61, "neutralPct": 6}, "oi": 3280560, "oiChange": 0, "volume": 525125460, "price": 96.3, "change": -27.5, "signals": {"liq": "BSL", "bos": "DOWN", "delta": -0.603, "trap": false, "oiInterp": null, "iv": 0.044, "gamma": 0.00218, "theta": -25.89, "vega": 15.53}, "velocity": "WARM"}}, {"strike": 77100, "label": "OTM+2", "isATM": false, "ce": {"signal": "SELL", "score": -27.0, "breakdown": {"buyPct": 38, "sellPct": 55, "neutralPct": 7}, "oi": 2818680, "oiChange": 0, "volume": 592935480, "price": 0.25, "change": -568.6, "signals": {"liq": "BSL", "bos": "DOWN", "delta": 0.483, "trap": false, "oiInterp": null, "iv": null, "gamma": null, "theta": null, "vega": null}, "velocity": "COLD"}, "pe": {"signal": "NEUTRAL", "score": 9.9, "breakdown": {"buyPct": 49, "sellPct": 43, "neutralPct": 8}, "oi": 914880, "oiChange": 0, "volume": 226712360, "price": 197.05, "change": 49.2, "signals": {"liq": "BSL", "bos": "DOWN", "delta": -0.704, "trap": false, "oiInterp": null, "iv": 0.0675, "gamma": 0.00127, "theta": -37.28, "vega": 13.91}, "velocity": "COLD"}}, {"strike": 77200, "label": "OTM+3", "isATM": false, "ce": {"signal": "SELL", "score": -19.5, "breakdown": {"buyPct": 39, "sellPct": 53, "neutralPct": 8}, "oi": 2612680, "oiChange": 0, "volume": 615035880, "price": 0.2, "change": -498.9, "signals": {"liq": "BSL", "bos": "DOWN", "delta": 0.473, "trap": false, "oiInterp": null, "iv": null, "gamma": null, "theta": null, "vega": null}, "velocity": "COLD"}, "pe": {"signal": "NEUTRAL", "score": 0.7, "breakdown": {"buyPct": 46, "sellPct": 45, "neutralPct": 9}, "oi": 731120, "oiChange": 0, "volume": 113696080, "price": 296.95, "change": 120.05, "signals": {"liq": "BSL", "bos": "DOWN", "delta": -0.757, "trap": false, "oiInterp": null, "iv": 0.0875, "gamma": 0.00089, "theta": -44.76, "vega": 12.61}, "velocity": "COLD"}}, {"strike": 77300, "label": "OTM+4", "isATM": false, "ce": {"signal": "SELL", "score": -19.4, "breakdown": {"buyPct": 39, "sellPct": 53, "neutralPct": 8}, "oi": 2513220, "oiChange": 0, "volume": 455667720, "price": 0.1, "change": -433.7, "signals": {"liq": "BSL", "bos": "DOWN", "delta": 0.463, "trap": false, "oiInterp": null, "iv": null, "gamma": null, "theta": null, "vega": null}, "velocity": "COLD"}, "pe": {"signal": "NEUTRAL", "score": -6.6, "breakdown": {"buyPct": 43, "sellPct": 48, "neutralPct": 9}, "oi": 313200, "oiChange": 0, "volume": 37556760, "price": 396.95, "change": 187.8, "signals": {"liq": "BSL", "bos": "DOWN", "delta": -0.79, "trap": false, "oiInterp": null, "iv": 0.106, "gamma": 0.00067, "theta": -50.6, "vega": 11.6}, "velocity": "COLD"}}, {"strike": 77400, "label": "OTM+5", "isATM": false, "ce": {"signal": "SELL", "score": -18.4, "breakdown": {"buyPct": 40, "sellPct": 52, "neutralPct": 8}, "oi": 1708140, "oiChange": 0, "volume": 326462520, "price": 0.15, "change": -370.05, "signals": {"liq": "BSL", "bos": "DOWN", "delta": 0.452, "trap": false, "oiInterp": null, "iv": null, "gamma": null, "theta": null, "vega": null}, "velocity": "COLD"}, "pe": {"signal": "NEUTRAL", "score": -9.5, "breakdown": {"buyPct": 43, "sellPct": 49, "neutralPct": 8}, "oi": 150020, "oiChange": 0, "volume": 13977780, "price": 497.0, "change": 247.5, "signals": {"liq": "BSL", "bos": "DOWN", "delta": -0.814, "trap": false, "oiInterp": null, "iv": 0.1236, "gamma": 0.00054, "theta": -55.53, "vega": 10.8}, "velocity": "COLD"}}, {"strike": 77500, "label": "OTM+6", "isATM": false, "ce": {"signal": "SELL", "score": -19.9, "breakdown": {"buyPct": 40, "sellPct": 53, "neutralPct": 7}, "oi": 3139300, "oiChange": 0, "volume": 356626240, "price": 0.15, "change": -320.05, "signals": {"liq": "BSL", "bos": "DOWN", "delta": 0.442, "trap": false, "oiInterp": null, "iv": null, "gamma": null, "theta": null, "vega": null}, "velocity": "COLD"}, "pe": {"signal": "NEUTRAL", "score": -9.3, "breakdown": {"buyPct": 43, "sellPct": 49, "neutralPct": 8}, "oi": 206380, "oiChange": 0, "volume": 14443340, "price": 597.55, "change": 307.5, "signals": {"liq": "BSL", "bos": "DOWN", "delta": -0.83, "trap": false, "oiInterp": null, "iv": 0.1409, "gamma": 0.00045, "theta": -60.21, "vega": 10.18}, "velocity": "COLD"}}], "intelligence": {"symbol": "SENSEX", "signal": "STRONG_SELL", "score": -34.4, "confidence": 90, "regime": "TRENDING", "agreementPct": 89, "bullPressure": 22, "bearPressure": 78, "trapRiskPct": 0, "actionability": "HIGH", "confidenceReason": "Live chain with current confidence model", "pcr": 1.0, "maxPain": 76900, "maxPainGapPct": -0.05, "keyLevels": {"support": 76900, "resistance": 77000, "supportGapPct": 0.05, "resistanceGapPct": 0.08}, "bestStrike": {"strike": 76900, "label": "ATM", "side": "CE", "direction": "UP", "score": 90.5, "confidence": 100, "reason": "STRONG SELL CE at ATM (75% conviction) (EXTREME heat)", "greeksSummary": "\u03940.50 | \u03980 | \u03c30%"}, "pricePredictions": {"lowestItmCe": {"price": 8.7, "strike": 76900, "direction": "DOWN", "confidence": 85, "signal": "STRONG_SELL", "velocity": "EXTREME"}, "lowestOtmCe": {"price": 0.1, "strike": 77300, "direction": "DOWN", "confidence": 55, "signal": "SELL", "velocity": "COLD"}, "lowestItmPe": {"price": 96.3, "strike": 77000, "direction": "DOWN", "confidence": 60, "signal": "SELL", "velocity": "WARM"}, "lowestOtmPe": {"price": 0.1, "strike": 76500, "direction": "DOWN", "confidence": 40, "signal": "NEUTRAL", "velocity": "COLD"}}, "insights": ["Flow bias: STRONG SELL (-34.4)", "Agreement 89% across active strikes", "Key levels S:76900 | R:77000", "BOS confirms downside continuation"]}, "dataSource": "LAST_CLOSE", "timestamp": "2026-04-30T15:22:19.929950+05:30", "spotUpdatedAt": "2026-04-30T15:22:19.929950+05:30", "optionChainUpdatedAt": "2026-04-30T15:22:13.965372+05:30", "optionChainAgeSec": 256626.6, "feedMode": "HYBRID_LIVE"}}